asqlite/__init__.py
asqlite/py.typed
asqlite-2.0.0.dist-info/LICENSE
asqlite-2.0.0.dist-info/METADATA
asqlite-2.0.0.dist-info/WHEEL
asqlite-2.0.0.dist-info/top_level.txt
asqlite-2.0.0.dist-info/RECORD
