Metadata-Version: 2.1
Name: asqlite
Version: 2.0.0
Summary: A simple and easy to use async wrapper for sqlite3.
Home-page: https://github.com/Rapptz/asqlite/
Author: Rapptz
License: MIT
Project-URL: Issue Tracker, https://github.com/Rapptz/asqlite/issues/
Classifier: License :: OSI Approved :: MIT License
Classifier: Intended Audience :: Developers
Classifier: Natural Language :: English
Classifier: Operating System :: OS Independent
Classifier: Programming Language :: Python :: 3.8
Classifier: Programming Language :: Python :: 3.9
Classifier: Programming Language :: Python :: 3.10
Requires-Python: >=3.8.0
License-File: LICENSE
